jumpcloud_aws_cli/__init__.py
jumpcloud_aws_cli/auth.py
jumpcloud_aws_cli/cli.py
jumpcloud_awscli-0.2.1.dist-info/licenses/LICENSE
jumpcloud_awscli-0.2.1.dist-info/METADATA
jumpcloud_awscli-0.2.1.dist-info/WHEEL
jumpcloud_awscli-0.2.1.dist-info/entry_points.txt
jumpcloud_awscli-0.2.1.dist-info/top_level.txt
jumpcloud_awscli-0.2.1.dist-info/RECORD
