Metadata-Version: 2.4
Name: jumpcloud-awscli
Version: 0.2.1
Summary: JumpCloud AWS CLI Authentication with Device Trust
Home-page: https://github.com/prashantbanthia/jumpcloud-awscli
Author: Prashant Banthia
Author-email: Prashant Banthia <prashantbanthia98@gmail.com>
License: MIT
Project-URL: Homepage, https://github.com/prashantbanthia/jumpcloud-awscli
Project-URL: Bug Tracker, https://github.com/prashantbanthia/jumpcloud-awscli/issues
Classifier: Development Status :: 3 - Alpha
Classifier: Intended Audience :: Developers
Classifier: Intended Audience :: System Administrators
Classifier: License :: OSI Approved :: MIT License
Classifier: Operating System :: OS Independent
Classifier: Programming Language :: Python :: 3
Classifier: Programming Language :: Python :: 3.6
Classifier: Programming Language :: Python :: 3.7
Classifier: Programming Language :: Python :: 3.8
Classifier: Programming Language :: Python :: 3.9
Classifier: Topic :: System :: Systems Administration
Classifier: Topic :: Utilities
Requires-Python: >=3.6
License-File: LICENSE
Requires-Dist: boto3>=1.20.0
Requires-Dist: requests>=2.25.0
Requires-Dist: selenium>=4.0.0
Requires-Dist: beautifulsoup4>=4.9.0
Requires-Dist: configparser>=5.0.0
Provides-Extra: auto-webdriver
Requires-Dist: webdriver-manager>=4.0.0; extra == "auto-webdriver"
Dynamic: author
Dynamic: home-page
Dynamic: license-file
Dynamic: requires-python
